[
  {
    "Type": "DataTable",
    "Name": "DT_PacenoteHafrenNorthReverseCut2",
    "Class": "UScriptClass'DataTable'",
    "Flags": "RF_Public | RF_Standalone | RF_Transactional | RF_WasLoaded | RF_LoadCompleted",
    "Properties": {
      "RowStruct": {
        "ObjectName": "Class'PacenoteSplineEntry'",
        "ObjectPath": "/Script/acr"
      }
    },
    "Rows": {
      "R0000": {
        "SplineDistanceM": 329.9064,
        "LengthM": 101.53433,
        "TokenList": {
          "Tokens": [
            "Right3",
            "Long"
          ]
        },
        "LinkToNext": true,
        "Description": "",
        "SavedLocation": {
          "X": 0.0,
          "Y": 0.0,
          "Z": 0.0
        }
      },
      "R0001": {
        "SplineDistanceM": 460.29346,
        "LengthM": 45.57199,
        "TokenList": {
          "Tokens": [
            "And",
            "KinksStartingLeft"
          ]
        },
        "LinkToNext": true,
        "Description": "",
        "SavedLocation": {
          "X": 0.0,
          "Y": 0.0,
          "Z": 0.0
        }
      },
      "R0002": {
        "SplineDistanceM": 507.31772,
        "LengthM": 41.73156,
        "TokenList": {
          "Tokens": [
            "Dist40"
          ]
        },
        "LinkToNext": false,
        "Description": "",
        "SavedLocation": {
          "X": 0.0,
          "Y": 0.0,
          "Z": 0.0
        }
      },
      "R0003": {
        "SplineDistanceM": 556.2586,
        "LengthM": 115.379295,
        "TokenList": {
          "Tokens": [
            "Left3",
            "Long"
          ]
        },
        "LinkToNext": true,
        "Description": "",
        "SavedLocation": {
          "X": 0.0,
          "Y": 0.0,
          "Z": 0.0
        }
      },
      "R0004": {
        "SplineDistanceM": 677.1748,
        "LengthM": 71.530235,
        "TokenList": {
          "Tokens": [
            "Dist70"
          ]
        },
        "LinkToNext": false,
        "Description": "",
        "SavedLocation": {
          "X": 0.0,
          "Y": 0.0,
          "Z": 0.0
        }
      },
      "R0005": {
        "SplineDistanceM": 750.7882,
        "LengthM": 63.60953,
        "TokenList": {
          "Tokens": [
            "KinksStartingRight"
          ]
        },
        "LinkToNext": true,
        "Description": "",
        "SavedLocation": {
          "X": 0.0,
          "Y": 0.0,
          "Z": 0.0
        }
      },
      "R0006": {
        "SplineDistanceM": 816.4719,
        "LengthM": 45.73375,
        "TokenList": {
          "Tokens": [
            "Into",
            "Right5",
            "OverCrest"
          ]
        },
        "LinkToNext": true,
        "Description": "",
        "SavedLocation": {
          "X": 0.0,
          "Y": 0.0,
          "Z": 0.0
        }
      },
      "R0007": {
        "SplineDistanceM": 864.21277,
        "LengthM": 60.191006,
        "TokenList": {
          "Tokens": [
            "Dist60"
          ]
        },
        "LinkToNext": false,
        "Description": "",
        "SavedLocation": {
          "X": 0.0,
          "Y": 0.0,
          "Z": 0.0
        }
      },
      "R0008": {
        "SplineDistanceM": 926.33813,
        "LengthM": 38.58203,
        "TokenList": {
          "Tokens": [
            "GoStraight"
          ]
        },
        "LinkToNext": true,
        "Description": "",
        "SavedLocation": {
          "X": 0.0,
          "Y": 0.0,
          "Z": 0.0
        }
      },
      "R0009": {
        "SplineDistanceM": 967.98944,
        "LengthM": 56.33492,
        "TokenList": {
          "Tokens": [
            "Into",
            "Left4",
            "Tightens",
            "OverCrest"
          ]
        },
        "LinkToNext": true,
        "Description": "",
        "SavedLocation": {
          "X": 0.0,
          "Y": 0.0,
          "Z": 0.0
        }
      },
      "R0010": {
        "SplineDistanceM": 1032.4243,
        "LengthM": 62.535778,
        "TokenList": {
          "Tokens": [
            "And",
            "Right5",
            "KeepIn"
          ]
        },
        "LinkToNext": false,
        "Description": "",
        "SavedLocation": {
          "X": 0.0,
          "Y": 0.0,
          "Z": 0.0
        }
      },
      "R0011": {
        "SplineDistanceM": 1117.7792,
        "LengthM": 61.053436,
        "TokenList": {
          "Tokens": [
            "Into",
            "Right3",
            "Tightens",
            "OverCrest"
          ]
        },
        "LinkToNext": false,
        "Description": "",
        "SavedLocation": {
          "X": 0.0,
          "Y": 0.0,
          "Z": 0.0
        }
      },
      "R0012": {
        "SplineDistanceM": 1201.6842,
        "LengthM": 127.48912,
        "TokenList": {
          "Tokens": [
            "Left4",
            "VeryLong"
          ]
        },
        "LinkToNext": true,
        "Description": "",
        "SavedLocation": {
          "X": 0.0,
          "Y": 0.0,
          "Z": 0.0
        }
      },
      "R0013": {
        "SplineDistanceM": 1329.7767,
        "LengthM": 24.980312,
        "TokenList": {
          "Tokens": [
            "Crest"
          ]
        },
        "LinkToNext": true,
        "Description": "",
        "SavedLocation": {
          "X": 0.0,
          "Y": 0.0,
          "Z": 0.0
        }
      },
      "R0014": {
        "SplineDistanceM": 1356.3053,
        "LengthM": 64.55484,
        "TokenList": {
          "Tokens": [
            "Into",
            "Left3"
          ]
        },
        "LinkToNext": false,
        "Description": "",
        "SavedLocation": {
          "X": 0.0,
          "Y": 0.0,
          "Z": 0.0
        }
      },
      "R0015": {
        "SplineDistanceM": 1422.8019,
        "LengthM": 45.0975,
        "TokenList": {
          "Tokens": [
            "Dist40"
          ]
        },
        "LinkToNext": false,
        "Description": "",
        "SavedLocation": {
          "X": 0.0,
          "Y": 0.0,
          "Z": 0.0
        }
      },
      "R0016": {
        "SplineDistanceM": 1469.8507,
        "LengthM": 69.016716,
        "TokenList": {
          "Tokens": [
            "KinksStartingRight"
          ]
        },
        "LinkToNext": false,
        "Description": "",
        "SavedLocation": {
          "X": 0.0,
          "Y": 0.0,
          "Z": 0.0
        }
      },
      "R0017": {
        "SplineDistanceM": 1541.6736,
        "LengthM": 35.253437,
        "TokenList": {
          "Tokens": [
            "Brake",
            "Right5"
          ]
        },
        "LinkToNext": true,
        "Description": "",
        "SavedLocation": {
          "X": 0.0,
          "Y": 0.0,
          "Z": 0.0
        }
      },
      "R0018": {
        "SplineDistanceM": 1580.2301,
        "LengthM": 58.83828,
        "TokenList": {
          "Tokens": [
            "Into",
            "Right2"
          ]
        },
        "LinkToNext": false,
        "Description": "",
        "SavedLocation": {
          "X": 0.0,
          "Y": 0.0,
          "Z": 0.0
        }
      },
      "R0019": {
        "SplineDistanceM": 1658.7881,
        "LengthM": 33.634686,
        "TokenList": {
          "Tokens": [
            "And",
            "Left4",
            "Short"
          ]
        },
        "LinkToNext": false,
        "Description": "",
        "SavedLocation": {
          "X": 0.0,
          "Y": 0.0,
          "Z": 0.0
        }
      },
      "R0020": {
        "SplineDistanceM": 1709.1614,
        "LengthM": 76.807495,
        "TokenList": {
          "Tokens": [
            "And",
            "KinksStartingLeft",
            "DontCut"
          ]
        },
        "LinkToNext": true,
        "Description": "",
        "SavedLocation": {
          "X": 0.0,
          "Y": 0.0,
          "Z": 0.0
        }
      },
      "R0021": {
        "SplineDistanceM": 1799.1013,
        "LengthM": 53.164997,
        "TokenList": {
          "Tokens": [
            "Into",
            "Left5"
          ]
        },
        "LinkToNext": true,
        "Description": "",
        "SavedLocation": {
          "X": 0.0,
          "Y": 0.0,
          "Z": 0.0
        }
      },
      "R0022": {
        "SplineDistanceM": 1853.9575,
        "LengthM": 25.706562,
        "TokenList": {
          "Tokens": [
            "Into",
            "Right4",
            "Short",
            "OverCrest"
          ]
        },
        "LinkToNext": false,
        "Description": "",
        "SavedLocation": {
          "X": 0.0,
          "Y": 0.0,
          "Z": 0.0
        }
      },
      "R0023": {
        "SplineDistanceM": 1903.8876,
        "LengthM": 62.723278,
        "TokenList": {
          "Tokens": [
            "And",
            "Right4"
          ]
        },
        "LinkToNext": false,
        "Description": "",
        "SavedLocation": {
          "X": 0.0,
          "Y": 0.0,
          "Z": 0.0
        }
      },
      "R0024": {
        "SplineDistanceM": 1975.9226,
        "LengthM": 47.759842,
        "TokenList": {
          "Tokens": [
            "Into",
            "Left3",
            "Tightens"
          ]
        },
        "LinkToNext": true,
        "Description": "",
        "SavedLocation": {
          "X": 0.0,
          "Y": 0.0,
          "Z": 0.0
        }
      },
      "R0025": {
        "SplineDistanceM": 2027.292,
        "LengthM": 98.18609,
        "TokenList": {
          "Tokens": [
            "Dist100"
          ]
        },
        "LinkToNext": false,
        "Description": "",
        "SavedLocation": {
          "X": 0.0,
          "Y": 0.0,
          "Z": 0.0
        }
      },
      "R0026": {
        "SplineDistanceM": 2130.1548,
        "LengthM": 55.25625,
        "TokenList": {
          "Tokens": [
            "Left4"
          ]
        },
        "LinkToNext": false,
        "Description": "",
        "SavedLocation": {
          "X": 0.0,
          "Y": 0.0,
          "Z": 0.0
        }
      },
      "R0027": {
        "SplineDistanceM": 2204.957,
        "LengthM": 67.542656,
        "TokenList": {
          "Tokens": [
            "And",
            "Right5"
          ]
        },
        "LinkToNext": true,
        "Description": "",
        "SavedLocation": {
          "X": 0.0,
          "Y": 0.0,
          "Z": 0.0
        }
      },
      "R0028": {
        "SplineDistanceM": 2275.8289,
        "LengthM": 41.390156,
        "TokenList": {
          "Tokens": [
            "Into",
            "Left3"
          ]
        },
        "LinkToNext": true,
        "Description": "",
        "SavedLocation": {
          "X": 0.0,
          "Y": 0.0,
          "Z": 0.0
        }
      },
      "R0029": {
        "SplineDistanceM": 2322.1333,
        "LengthM": 70.674995,
        "TokenList": {
          "Tokens": [
            "Dist70"
          ]
        },
        "LinkToNext": false,
        "Description": "",
        "SavedLocation": {
          "X": 0.0,
          "Y": 0.0,
          "Z": 0.0
        }
      },
      "R0030": {
        "SplineDistanceM": 2395.7998,
        "LengthM": 45.31734,
        "TokenList": {
          "Tokens": [
            "Right2"
          ]
        },
        "LinkToNext": true,
        "Description": "",
        "SavedLocation": {
          "X": 0.0,
          "Y": 0.0,
          "Z": 0.0
        }
      },
      "R0031": {
        "SplineDistanceM": 2443.5415,
        "LengthM": 36.5575,
        "TokenList": {
          "Tokens": [
            "Into",
            "Left1"
          ]
        },
        "LinkToNext": true,
        "Description": "",
        "SavedLocation": {
          "X": 0.0,
          "Y": 0.0,
          "Z": 0.0
        }
      },
      "R0032": {
        "SplineDistanceM": 2482.7988,
        "LengthM": 44.21875,
        "TokenList": {
          "Tokens": [
            "Dist40",
            "Narrows"
          ]
        },
        "LinkToNext": false,
        "Description": "",
        "SavedLocation": {
          "X": 0.0,
          "Y": 0.0,
          "Z": 0.0
        }
      },
      "R0033": {
        "SplineDistanceM": 2529.8604,
        "LengthM": 39.39609,
        "TokenList": {
          "Tokens": [
            "Right5"
          ]
        },
        "LinkToNext": false,
        "Description": "",
        "SavedLocation": {
          "X": 0.0,
          "Y": 0.0,
          "Z": 0.0
        }
      },
      "R0034": {
        "SplineDistanceM": 2580.7793,
        "LengthM": 42.789062,
        "TokenList": {
          "Tokens": [
            "And",
            "KinksStartingRight",
            "OverBumps"
          ]
        },
        "LinkToNext": true,
        "Description": "",
        "SavedLocation": {
          "X": 0.0,
          "Y": 0.0,
          "Z": 0.0
        }
      },
      "R0035": {
        "SplineDistanceM": 2625.7026,
        "LengthM": 39.47781,
        "TokenList": {
          "Tokens": [
            "Dist40"
          ]
        },
        "LinkToNext": false,
        "Description": "",
        "SavedLocation": {
          "X": 0.0,
          "Y": 0.0,
          "Z": 0.0
        }
      },
      "R0036": {
        "SplineDistanceM": 2666.6643,
        "LengthM": 34.84156,
        "TokenList": {
          "Tokens": [
            "RightFlat"
          ]
        },
        "LinkToNext": true,
        "Description": "",
        "SavedLocation": {
          "X": 0.0,
          "Y": 0.0,
          "Z": 0.0
        }
      },
      "R0037": {
        "SplineDistanceM": 2703.4875,
        "LengthM": 39.512188,
        "TokenList": {
          "Tokens": [
            "Dist40"
          ]
        },
        "LinkToNext": false,
        "Description": "",
        "SavedLocation": {
          "X": 0.0,
          "Y": 0.0,
          "Z": 0.0
        }
      },
      "R0038": {
        "SplineDistanceM": 2743.8486,
        "LengthM": 25.187187,
        "TokenList": {
          "Tokens": [
            "Right6",
            "Short"
          ]
        },
        "LinkToNext": true,
        "Description": "",
        "SavedLocation": {
          "X": 0.0,
          "Y": 0.0,
          "Z": 0.0
        }
      },
      "R0039": {
        "SplineDistanceM": 2770.2026,
        "LengthM": 38.38031,
        "TokenList": {
          "Tokens": [
            "Dist40"
          ]
        },
        "LinkToNext": false,
        "Description": "",
        "SavedLocation": {
          "X": 0.0,
          "Y": 0.0,
          "Z": 0.0
        }
      },
      "R0040": {
        "SplineDistanceM": 2809.4534,
        "LengthM": 54.524685,
        "TokenList": {
          "Tokens": [
            "Right6",
            "KeepIn"
          ]
        },
        "LinkToNext": true,
        "Description": "",
        "SavedLocation": {
          "X": 0.0,
          "Y": 0.0,
          "Z": 0.0
        }
      },
      "R0041": {
        "SplineDistanceM": 2867.2327,
        "LengthM": 80.60749,
        "TokenList": {
          "Tokens": [
            "Dist80",
            "OverCrest"
          ]
        },
        "LinkToNext": false,
        "Description": "",
        "SavedLocation": {
          "X": 0.0,
          "Y": 0.0,
          "Z": 0.0
        }
      },
      "R0042": {
        "SplineDistanceM": 2958.2517,
        "LengthM": 68.57624,
        "TokenList": {
          "Tokens": [
            "Left4",
            "Tightens"
          ]
        },
        "LinkToNext": true,
        "Description": "",
        "SavedLocation": {
          "X": 0.0,
          "Y": 0.0,
          "Z": 0.0
        }
      },
      "R0043": {
        "SplineDistanceM": 3045.7634,
        "LengthM": 78.752495,
        "TokenList": {
          "Tokens": [
            "Dist80"
          ]
        },
        "LinkToNext": false,
        "Description": "",
        "SavedLocation": {
          "X": 0.0,
          "Y": 0.0,
          "Z": 0.0
        }
      },
      "R0044": {
        "SplineDistanceM": 3130.217,
        "LengthM": 56.46781,
        "TokenList": {
          "Tokens": [
            "Dip",
            "Left3",
            "KeepIn"
          ]
        },
        "LinkToNext": true,
        "Description": "",
        "SavedLocation": {
          "X": 0.0,
          "Y": 0.0,
          "Z": 0.0
        }
      },
      "R0045": {
        "SplineDistanceM": 3188.797,
        "LengthM": 55.82906,
        "TokenList": {
          "Tokens": [
            "Dist50",
            "OverCrest"
          ]
        },
        "LinkToNext": false,
        "Description": "",
        "SavedLocation": {
          "X": 0.0,
          "Y": 0.0,
          "Z": 0.0
        }
      },
      "R0046": {
        "SplineDistanceM": 3247.6868,
        "LengthM": 59.306248,
        "TokenList": {
          "Tokens": [
            "Left3",
            "Tightens"
          ]
        },
        "LinkToNext": true,
        "Description": "",
        "SavedLocation": {
          "X": 0.0,
          "Y": 0.0,
          "Z": 0.0
        }
      },
      "R0047": {
        "SplineDistanceM": 3309.95,
        "LengthM": 36.085938,
        "TokenList": {
          "Tokens": [
            "Caution",
            "Right4"
          ]
        },
        "LinkToNext": false,
        "Description": "",
        "SavedLocation": {
          "X": 0.0,
          "Y": 0.0,
          "Z": 0.0
        }
      },
      "R0048": {
        "SplineDistanceM": 3365.008,
        "LengthM": 38.9675,
        "TokenList": {
          "Tokens": [
            "Brake",
            "Left1"
          ]
        },
        "LinkToNext": true,
        "Description": "",
        "SavedLocation": {
          "X": 0.0,
          "Y": 0.0,
          "Z": 0.0
        }
      },
      "R0049": {
        "SplineDistanceM": 3407.95,
        "LengthM": 28.345,
        "TokenList": {
          "Tokens": [
            "And",
            "Sudden",
            "Right3",
            "Short"
          ]
        },
        "LinkToNext": true,
        "Description": "",
        "SavedLocation": {
          "X": 0.0,
          "Y": 0.0,
          "Z": 0.0
        }
      },
      "R0050": {
        "SplineDistanceM": 3441.2358,
        "LengthM": 208.7828,
        "TokenList": {
          "Tokens": [
            "Dist200",
            "OverCrest"
          ]
        },
        "LinkToNext": false,
        "Description": "",
        "SavedLocation": {
          "X": 0.0,
          "Y": 0.0,
          "Z": 0.0
        }
      },
      "R0051": {
        "SplineDistanceM": 3654.006,
        "LengthM": 47.45406,
        "TokenList": {
          "Tokens": [
            "Left2",
            "Tightens"
          ]
        },
        "LinkToNext": false,
        "Description": "",
        "SavedLocation": {
          "X": 0.0,
          "Y": 0.0,
          "Z": 0.0
        }
      },
      "R0052": {
        "SplineDistanceM": 3704.7869,
        "LengthM": 36.17625,
        "TokenList": {
          "Tokens": [
            "And",
            "Right4",
            "Short"
          ]
        },
        "LinkToNext": true,
        "Description": "",
        "SavedLocation": {
          "X": 0.0,
          "Y": 0.0,
          "Z": 0.0
        }
      },
      "R0053": {
        "SplineDistanceM": 3743.5527,
        "LengthM": 39.827183,
        "TokenList": {
          "Tokens": [
            "Dist40"
          ]
        },
        "LinkToNext": false,
        "Description": "",
        "SavedLocation": {
          "X": 0.0,
          "Y": 0.0,
          "Z": 0.0
        }
      },
      "R0054": {
        "SplineDistanceM": 3786.0137,
        "LengthM": 84.23125,
        "TokenList": {
          "Tokens": [
            "Left5",
            "Long",
            "OverCrest"
          ]
        },
        "LinkToNext": false,
        "Description": "",
        "SavedLocation": {
          "X": 0.0,
          "Y": 0.0,
          "Z": 0.0
        }
      },
      "R0055": {
        "SplineDistanceM": 3878.9233,
        "LengthM": 135.54282,
        "TokenList": {
          "Tokens": [
            "Into",
            "Right5",
            "Long",
            "TightensLate"
          ]
        },
        "LinkToNext": true,
        "Description": "",
        "SavedLocation": {
          "X": 0.0,
          "Y": 0.0,
          "Z": 0.0
        }
      },
      "R0056": {
        "SplineDistanceM": 4016.7004,
        "LengthM": 69.56344,
        "TokenList": {
          "Tokens": [
            "Dist70"
          ]
        },
        "LinkToNext": false,
        "Description": "",
        "SavedLocation": {
          "X": 0.0,
          "Y": 0.0,
          "Z": 0.0
        }
      },
      "R0057": {
        "SplineDistanceM": 4088.648,
        "LengthM": 48.933125,
        "TokenList": {
          "Tokens": [
            "Right4",
            "DontCut"
          ]
        },
        "LinkToNext": true,
        "Description": "",
        "SavedLocation": {
          "X": 0.0,
          "Y": 0.0,
          "Z": 0.0
        }
      },
      "R0058": {
        "SplineDistanceM": 4142.0596,
        "LengthM": 79.26093,
        "TokenList": {
          "Tokens": [
            "Dist80"
          ]
        },
        "LinkToNext": false,
        "Description": "",
        "SavedLocation": {
          "X": 0.0,
          "Y": 0.0,
          "Z": 0.0
        }
      },
      "R0059": {
        "SplineDistanceM": 4223.1436,
        "LengthM": 42.934063,
        "TokenList": {
          "Tokens": [
            "Left4"
          ]
        },
        "LinkToNext": false,
        "Description": "",
        "SavedLocation": {
          "X": 0.0,
          "Y": 0.0,
          "Z": 0.0
        }
      },
      "R0060": {
        "SplineDistanceM": 4281.4746,
        "LengthM": 66.455315,
        "TokenList": {
          "Tokens": [
            "Into",
            "Right3",
            "Tightens"
          ]
        },
        "LinkToNext": false,
        "Description": "",
        "SavedLocation": {
          "X": 0.0,
          "Y": 0.0,
          "Z": 0.0
        }
      },
      "R0061": {
        "SplineDistanceM": 4354.8267,
        "LengthM": 78.27125,
        "TokenList": {
          "Tokens": [
            "And",
            "Left4",
            "Long",
            "Opens"
          ]
        },
        "LinkToNext": false,
        "Description": "",
        "SavedLocation": {
          "X": 0.0,
          "Y": 0.0,
          "Z": 0.0
        }
      },
      "R0062": {
        "SplineDistanceM": 4436.7812,
        "LengthM": 249.665,
        "TokenList": {
          "Tokens": [
            "Into",
            "Right3",
            "VeryLong",
            "Pause0.1s_Reset",
            "Opens",
            "And",
            "TightensLate",
            "Pause0.1s_Reset",
            "LogsInside"
          ]
        },
        "LinkToNext": true,
        "Description": "",
        "SavedLocation": {
          "X": 0.0,
          "Y": 0.0,
          "Z": 0.0
        }
      },
      "R0063": {
        "SplineDistanceM": 4688.435,
        "LengthM": 82.887184,
        "TokenList": {
          "Tokens": [
            "Dist80"
          ]
        },
        "LinkToNext": false,
        "Description": "",
        "SavedLocation": {
          "X": 0.0,
          "Y": 0.0,
          "Z": 0.0
        }
      },
      "R0064": {
        "SplineDistanceM": 4773.243,
        "LengthM": 62.10781,
        "TokenList": {
          "Tokens": [
            "Left6"
          ]
        },
        "LinkToNext": true,
        "Description": "",
        "SavedLocation": {
          "X": 0.0,
          "Y": 0.0,
          "Z": 0.0
        }
      },
      "R0065": {
        "SplineDistanceM": 4837.695,
        "LengthM": 63.078747,
        "TokenList": {
          "Tokens": [
            "Dist60"
          ]
        },
        "LinkToNext": false,
        "Description": "",
        "SavedLocation": {
          "X": 0.0,
          "Y": 0.0,
          "Z": 0.0
        }
      },
      "R0066": {
        "SplineDistanceM": 4904.1426,
        "LengthM": 69.253746,
        "TokenList": {
          "Tokens": [
            "Left2",
            "Tighten1"
          ]
        },
        "LinkToNext": true,
        "Description": "",
        "SavedLocation": {
          "X": 0.0,
          "Y": 0.0,
          "Z": 0.0
        }
      },
      "R0067": {
        "SplineDistanceM": 4975.657,
        "LengthM": 38.25656,
        "TokenList": {
          "Tokens": [
            "Dist40"
          ]
        },
        "LinkToNext": false,
        "Description": "",
        "SavedLocation": {
          "X": 0.0,
          "Y": 0.0,
          "Z": 0.0
        }
      },
      "R0068": {
        "SplineDistanceM": 5017.002,
        "LengthM": 39.7375,
        "TokenList": {
          "Tokens": [
            "Left4"
          ]
        },
        "LinkToNext": false,
        "Description": "",
        "SavedLocation": {
          "X": 0.0,
          "Y": 0.0,
          "Z": 0.0
        }
      },
      "R0069": {
        "SplineDistanceM": 5060.393,
        "LengthM": 53.105938,
        "TokenList": {
          "Tokens": [
            "Right4",
            "DontCut"
          ]
        },
        "LinkToNext": false,
        "Description": "",
        "SavedLocation": {
          "X": 0.0,
          "Y": 0.0,
          "Z": 0.0
        }
      },
      "R0070": {
        "SplineDistanceM": 5140.75,
        "LengthM": 85.18656,
        "TokenList": {
          "Tokens": [
            "Into",
            "Right3",
            "Caution",
            "Tighten2",
            "Late",
            "DontCut"
          ]
        },
        "LinkToNext": false,
        "Description": "",
        "SavedLocation": {
          "X": 0.0,
          "Y": 0.0,
          "Z": 0.0
        }
      },
      "R0071": {
        "SplineDistanceM": 5236.4673,
        "LengthM": 69.07719,
        "TokenList": {
          "Tokens": [
            "Left5",
            "Opens"
          ]
        },
        "LinkToNext": true,
        "Description": "",
        "SavedLocation": {
          "X": 0.0,
          "Y": 0.0,
          "Z": 0.0
        }
      },
      "R0072": {
        "SplineDistanceM": 5307.8936,
        "LengthM": 51.981873,
        "TokenList": {
          "Tokens": [
            "Dist50"
          ]
        },
        "LinkToNext": false,
        "Description": "",
        "SavedLocation": {
          "X": 0.0,
          "Y": 0.0,
          "Z": 0.0
        }
      },
      "R0073": {
        "SplineDistanceM": 5362.697,
        "LengthM": 83.62688,
        "TokenList": {
          "Tokens": [
            "KinksStartingLeft"
          ]
        },
        "LinkToNext": false,
        "Description": "",
        "SavedLocation": {
          "X": 0.0,
          "Y": 0.0,
          "Z": 0.0
        }
      },
      "R0074": {
        "SplineDistanceM": 5466.9087,
        "LengthM": 79.87812,
        "TokenList": {
          "Tokens": [
            "And",
            "Right6"
          ]
        },
        "LinkToNext": true,
        "Description": "",
        "SavedLocation": {
          "X": 0.0,
          "Y": 0.0,
          "Z": 0.0
        }
      },
      "R0075": {
        "SplineDistanceM": 5548.964,
        "LengthM": 47.45,
        "TokenList": {
          "Tokens": [
            "Dist50"
          ]
        },
        "LinkToNext": false,
        "Description": "",
        "SavedLocation": {
          "X": 0.0,
          "Y": 0.0,
          "Z": 0.0
        }
      },
      "R0076": {
        "SplineDistanceM": 5597.3037,
        "LengthM": 71.07687,
        "TokenList": {
          "Tokens": [
            "Left2",
            "Long",
            "Opens"
          ]
        },
        "LinkToNext": false,
        "Description": "",
        "SavedLocation": {
          "X": 0.0,
          "Y": 0.0,
          "Z": 0.0
        }
      },
      "R0077": {
        "SplineDistanceM": 5670.655,
        "LengthM": 41.109375,
        "TokenList": {
          "Tokens": [
            "And",
            "Right3",
            "OverCrest"
          ]
        },
        "LinkToNext": true,
        "Description": "",
        "SavedLocation": {
          "X": 0.0,
          "Y": 0.0,
          "Z": 0.0
        }
      },
      "R0078": {
        "SplineDistanceM": 5713.3057,
        "LengthM": 32.306248,
        "TokenList": {
          "Tokens": [
            "Finish"
          ]
        },
        "LinkToNext": false,
        "Description": "",
        "SavedLocation": {
          "X": 0.0,
          "Y": 0.0,
          "Z": 0.0
        }
      },
      "R0079": {
        "SplineDistanceM": 5964.0806,
        "LengthM": 12.072497,
        "TokenList": {
          "Tokens": [
            "Pause0.5s",
            "SlowDown",
            "StopAtMarshals"
          ]
        },
        "LinkToNext": false,
        "Description": "",
        "SavedLocation": {
          "X": 0.0,
          "Y": 0.0,
          "Z": 0.0
        }
      }
    }
  }
]